clumsygrad/__init__.py
clumsygrad/activation.py
clumsygrad/grad.py
clumsygrad/loss.py
clumsygrad/math.py
clumsygrad/optimizer.py
clumsygrad/random.py
clumsygrad/tensor.py
clumsygrad-0.2.1.dist-info/licenses/LICENSE
clumsygrad-0.2.1.dist-info/METADATA
clumsygrad-0.2.1.dist-info/WHEEL
clumsygrad-0.2.1.dist-info/top_level.txt
clumsygrad-0.2.1.dist-info/RECORD
