Metadata-Version: 2.4
Name: clumsygrad
Version: 0.2.1
Summary: A minimal python library for automatic differentiation, built on top of NumPy.
Author: Sayan Gupta
Maintainer: Sayan Gupta
License-Expression: MIT
Project-URL: Homepage, https://github.com/Sayan-001/ClumsyGrad
Project-URL: Issues, https://github.com/Sayan-001/ClumsyGrad/issues
Keywords: autograd,automatic-differentiation,machine-learning
Classifier: Development Status :: 3 - Alpha
Classifier: Intended Audience :: Developers
Classifier: Intended Audience :: Science/Research
Classifier: Topic :: Scientific/Engineering :: Artificial Intelligence
Classifier: Programming Language :: Python :: 3
Classifier: Programming Language :: Python :: 3.9
Classifier: Programming Language :: Python :: 3.10
Classifier: Programming Language :: Python :: 3.11
Classifier: Programming Language :: Python :: 3.12
Classifier: Programming Language :: Python :: 3.13
Classifier: Programming Language :: Python :: 3 :: Only
Requires-Python: >=3.9
License-File: LICENSE
Requires-Dist: numpy>=2.0.0
Dynamic: license-file
